nugen/__init__.py
nugen/cli.py
nugen-24.6.1.dist-info/METADATA
nugen-24.6.1.dist-info/WHEEL
nugen-24.6.1.dist-info/entry_points.txt
nugen-24.6.1.dist-info/top_level.txt
nugen-24.6.1.dist-info/RECORD
