Metadata-Version: 2.1
Name: nugen
Version: 24.6.1
Requires-Dist: pytz
